sciPENN/Preprocessing.py
sciPENN/Utils.py
sciPENN/__init__.py
sciPENN/sciPENN_API.py
sciPENN/Data_Infrastructure/DataLoader.py
sciPENN/Data_Infrastructure/DataLoader_Constructor.py
sciPENN/Data_Infrastructure/Samplers.py
sciPENN/Data_Infrastructure/__init__.py
sciPENN/Network/Layers.py
sciPENN/Network/Losses.py
sciPENN/Network/Model.py
sciPENN/Network/__init__.py
sciPENN-0.9.6.dist-info/LICENSE.rtf
sciPENN-0.9.6.dist-info/METADATA
sciPENN-0.9.6.dist-info/WHEEL
sciPENN-0.9.6.dist-info/top_level.txt
sciPENN-0.9.6.dist-info/RECORD
