Metadata-Version: 2.1
Name: sciPENN
Version: 0.9.6
Summary: A package for integrative and predictive analysis of CITE-seq data
Home-page: https://github.com/jlakkis/sciPENN
Author: Justin Lakkis
Author-email: jlakks@gmail.com
License: UNKNOWN
Platform: UNKNOWN
Classifier: Programming Language :: Python :: 3
Classifier: License :: OSI Approved :: MIT License
Classifier: Operating System :: OS Independent
Requires-Python: >=3.7
License-File: LICENSE.rtf
Requires-Dist: torch (>=1.6.1)
Requires-Dist: numba (<=0.50.0)
Requires-Dist: scanpy (>=1.7.1)
Requires-Dist: pandas (>=1.1.5)
Requires-Dist: numpy (>=1.20.1)
Requires-Dist: scipy (>=1.6.1)
Requires-Dist: tqdm (>=4.59.0)
Requires-Dist: anndata (>=0.7.5)
